maoris_py-0.0.1.dist-info/METADATA
maoris_py-0.0.1.dist-info/WHEEL
maoris_py-0.0.1.dist-info/licenses/LICENSE.md
maoris_py/__init__.py
maoris_py/maoris_py.cpython-310-x86_64-linux-gnu.so
maoris_py-0.0.1.dist-info/RECORD
